{
  "type": "minecraft:crafting_shaped",
  "pattern": [
    "PBP",
    "ITI",
    "DCD"
  ],
  "key": {
    "I": {
      "tag": "forge:ingots/compressed_iron"
    },
    "B": {
      "tag": "forge:storage_blocks/compressed_iron"
    },
    "T": {
      "item": "pneumaticcraft:pressure_tube"
    },
    "C": {
      "item": "pneumaticcraft:pneumatic_cylinder"
    },
    "P": {
      "item": "pneumaticcraft:plastic"
    },
    "D": {
      "tag": "forge:gems/diamond"
    }
  },
  "result": {
    "item": "pneumaticcraft:jackhammer"
  }
}