{
  "type": "minecraft:block",
  "pools": [
    {
      "name": "reinforced_chest",
      "rolls": 1.0,
      "bonus_rolls": 0.0,
      "entries": [
        {
          "type": "minecraft:item",
          "functions": [
            {
              "function": "minecraft:copy_name",
              "source": "block_entity"
            },
            {
              "function": "pneumaticcraft:te_serializer"
            }
          ],
          "name": "pneumaticcraft:reinforced_chest"
        }
      ],
      "conditions": [
        {
          "condition": "minecraft:survives_explosion"
        }
      ]
    }
  ]
}